[
  {
    "value": "10",
    "frac": "0.1186",
    "table": "postcode_2020_1_all_simd_carstairs.rds",
    "field": "carstairs2011_sc_decile",
    "folder": "/conf/EAVE/GPanalysis/data/lookups",
    "date_last_modified": "2020-06-02 13:13:10"
  },
  {
    "value": "8",
    "frac": "0.1134",
    "table": "postcode_2020_1_all_simd_carstairs.rds",
    "field": "carstairs2011_sc_decile",
    "folder": "/conf/EAVE/GPanalysis/data/lookups",
    "date_last_modified": "2020-06-02 13:13:10"
  },
  {
    "value": "9",
    "frac": "0.1078",
    "table": "postcode_2020_1_all_simd_carstairs.rds",
    "field": "carstairs2011_sc_decile",
    "folder": "/conf/EAVE/GPanalysis/data/lookups",
    "date_last_modified": "2020-06-02 13:13:10"
  },
  {
    "value": "1",
    "frac": "0.1063",
    "table": "postcode_2020_1_all_simd_carstairs.rds",
    "field": "carstairs2011_sc_decile",
    "folder": "/conf/EAVE/GPanalysis/data/lookups",
    "date_last_modified": "2020-06-02 13:13:10"
  },
  {
    "value": "7",
    "frac": "0.1014",
    "table": "postcode_2020_1_all_simd_carstairs.rds",
    "field": "carstairs2011_sc_decile",
    "folder": "/conf/EAVE/GPanalysis/data/lookups",
    "date_last_modified": "2020-06-02 13:13:10"
  },
  {
    "value": "6",
    "frac": "0.0946",
    "table": "postcode_2020_1_all_simd_carstairs.rds",
    "field": "carstairs2011_sc_decile",
    "folder": "/conf/EAVE/GPanalysis/data/lookups",
    "date_last_modified": "2020-06-02 13:13:10"
  },
  {
    "value": "4",
    "frac": "0.0919",
    "table": "postcode_2020_1_all_simd_carstairs.rds",
    "field": "carstairs2011_sc_decile",
    "folder": "/conf/EAVE/GPanalysis/data/lookups",
    "date_last_modified": "2020-06-02 13:13:10"
  },
  {
    "value": "3",
    "frac": "0.09",
    "table": "postcode_2020_1_all_simd_carstairs.rds",
    "field": "carstairs2011_sc_decile",
    "folder": "/conf/EAVE/GPanalysis/data/lookups",
    "date_last_modified": "2020-06-02 13:13:10"
  },
  {
    "value": "5",
    "frac": "0.0889",
    "table": "postcode_2020_1_all_simd_carstairs.rds",
    "field": "carstairs2011_sc_decile",
    "folder": "/conf/EAVE/GPanalysis/data/lookups",
    "date_last_modified": "2020-06-02 13:13:10"
  },
  {
    "value": "2",
    "frac": "0.0871",
    "table": "postcode_2020_1_all_simd_carstairs.rds",
    "field": "carstairs2011_sc_decile",
    "folder": "/conf/EAVE/GPanalysis/data/lookups",
    "date_last_modified": "2020-06-02 13:13:10"
  }
]
