[
  {
    "value": null,
    "frac": "0.803733333333333",
    "table": "postcode_2020_1_all_simd_carstairs.rds",
    "field": "simd2006_emp_rank",
    "folder": "/conf/EAVE/GPanalysis/data/lookups",
    "date_last_modified": "2020-06-02 13:13:10"
  },
  {
    "value": "2915",
    "frac": "0.0261333333333333",
    "table": "postcode_2020_1_all_simd_carstairs.rds",
    "field": "simd2006_emp_rank",
    "folder": "/conf/EAVE/GPanalysis/data/lookups",
    "date_last_modified": "2020-06-02 13:13:10"
  },
  {
    "value": "4064",
    "frac": "0.0117333333333333",
    "table": "postcode_2020_1_all_simd_carstairs.rds",
    "field": "simd2006_emp_rank",
    "folder": "/conf/EAVE/GPanalysis/data/lookups",
    "date_last_modified": "2020-06-02 13:13:10"
  },
  {
    "value": "114",
    "frac": "0.0106666666666667",
    "table": "postcode_2020_1_all_simd_carstairs.rds",
    "field": "simd2006_emp_rank",
    "folder": "/conf/EAVE/GPanalysis/data/lookups",
    "date_last_modified": "2020-06-02 13:13:10"
  },
  {
    "value": "3584",
    "frac": "0.0106666666666667",
    "table": "postcode_2020_1_all_simd_carstairs.rds",
    "field": "simd2006_emp_rank",
    "folder": "/conf/EAVE/GPanalysis/data/lookups",
    "date_last_modified": "2020-06-02 13:13:10"
  },
  {
    "value": "5679",
    "frac": "0.0101333333333333",
    "table": "postcode_2020_1_all_simd_carstairs.rds",
    "field": "simd2006_emp_rank",
    "folder": "/conf/EAVE/GPanalysis/data/lookups",
    "date_last_modified": "2020-06-02 13:13:10"
  },
  {
    "value": "3509",
    "frac": "0.00853333333333333",
    "table": "postcode_2020_1_all_simd_carstairs.rds",
    "field": "simd2006_emp_rank",
    "folder": "/conf/EAVE/GPanalysis/data/lookups",
    "date_last_modified": "2020-06-02 13:13:10"
  },
  {
    "value": "3820",
    "frac": "0.00853333333333333",
    "table": "postcode_2020_1_all_simd_carstairs.rds",
    "field": "simd2006_emp_rank",
    "folder": "/conf/EAVE/GPanalysis/data/lookups",
    "date_last_modified": "2020-06-02 13:13:10"
  },
  {
    "value": "4897",
    "frac": "0.00853333333333333",
    "table": "postcode_2020_1_all_simd_carstairs.rds",
    "field": "simd2006_emp_rank",
    "folder": "/conf/EAVE/GPanalysis/data/lookups",
    "date_last_modified": "2020-06-02 13:13:10"
  },
  {
    "value": "1039",
    "frac": "0.00746666666666667",
    "table": "postcode_2020_1_all_simd_carstairs.rds",
    "field": "simd2006_emp_rank",
    "folder": "/conf/EAVE/GPanalysis/data/lookups",
    "date_last_modified": "2020-06-02 13:13:10"
  }
]
