[
  {
    "value": "S22000065",
    "frac": "0.213027816690014",
    "table": "Scottish_Postcode_Directory_2021_2.rds",
    "field": "ttwa_2011",
    "folder": "/conf/EAVE/GPanalysis/data/lookups",
    "date_last_modified": "2021-10-28 14:55:27"
  },
  {
    "value": "S22000047",
    "frac": "0.115569341604963",
    "table": "Scottish_Postcode_Directory_2021_2.rds",
    "field": "ttwa_2011",
    "folder": "/conf/EAVE/GPanalysis/data/lookups",
    "date_last_modified": "2021-10-28 14:55:27"
  },
  {
    "value": "S22000059",
    "frac": "0.115069041424855",
    "table": "Scottish_Postcode_Directory_2021_2.rds",
    "field": "ttwa_2011",
    "folder": "/conf/EAVE/GPanalysis/data/lookups",
    "date_last_modified": "2021-10-28 14:55:27"
  },
  {
    "value": "S22000071",
    "frac": "0.0573344006403842",
    "table": "Scottish_Postcode_Directory_2021_2.rds",
    "field": "ttwa_2011",
    "folder": "/conf/EAVE/GPanalysis/data/lookups",
    "date_last_modified": "2021-10-28 14:55:27"
  },
  {
    "value": "S22000056",
    "frac": "0.0459275565339204",
    "table": "Scottish_Postcode_Directory_2021_2.rds",
    "field": "ttwa_2011",
    "folder": "/conf/EAVE/GPanalysis/data/lookups",
    "date_last_modified": "2021-10-28 14:55:27"
  },
  {
    "value": "S22000057",
    "frac": "0.04342605563338",
    "table": "Scottish_Postcode_Directory_2021_2.rds",
    "field": "ttwa_2011",
    "folder": "/conf/EAVE/GPanalysis/data/lookups",
    "date_last_modified": "2021-10-28 14:55:27"
  },
  {
    "value": "S22000061",
    "frac": "0.04342605563338",
    "table": "Scottish_Postcode_Directory_2021_2.rds",
    "field": "ttwa_2011",
    "folder": "/conf/EAVE/GPanalysis/data/lookups",
    "date_last_modified": "2021-10-28 14:55:27"
  },
  {
    "value": "S22000069",
    "frac": "0.0348208925355213",
    "table": "Scottish_Postcode_Directory_2021_2.rds",
    "field": "ttwa_2011",
    "folder": "/conf/EAVE/GPanalysis/data/lookups",
    "date_last_modified": "2021-10-28 14:55:27"
  },
  {
    "value": "S22000060",
    "frac": "0.03412047228337",
    "table": "Scottish_Postcode_Directory_2021_2.rds",
    "field": "ttwa_2011",
    "folder": "/conf/EAVE/GPanalysis/data/lookups",
    "date_last_modified": "2021-10-28 14:55:27"
  },
  {
    "value": "S22000074",
    "frac": "0.0272163297978787",
    "table": "Scottish_Postcode_Directory_2021_2.rds",
    "field": "ttwa_2011",
    "folder": "/conf/EAVE/GPanalysis/data/lookups",
    "date_last_modified": "2021-10-28 14:55:27"
  }
]
