[
  {
    "value": "2020-01-13",
    "frac": "0.0037359900373599",
    "table": "all_deaths.rds",
    "field": "NRS.Reg.Date",
    "folder": "/conf/EAVE/GPanalysis/data",
    "date_last_modified": "2022-08-11 11:36:22"
  },
  {
    "value": "2020-03-27",
    "frac": "0.0037359900373599",
    "table": "all_deaths.rds",
    "field": "NRS.Reg.Date",
    "folder": "/conf/EAVE/GPanalysis/data",
    "date_last_modified": "2022-08-11 11:36:22"
  },
  {
    "value": "2021-12-30",
    "frac": "0.00350956639873203",
    "table": "all_deaths.rds",
    "field": "NRS.Reg.Date",
    "folder": "/conf/EAVE/GPanalysis/data",
    "date_last_modified": "2022-08-11 11:36:22"
  },
  {
    "value": "2020-04-15",
    "frac": "0.00339635457941809",
    "table": "all_deaths.rds",
    "field": "NRS.Reg.Date",
    "folder": "/conf/EAVE/GPanalysis/data",
    "date_last_modified": "2022-08-11 11:36:22"
  },
  {
    "value": "2021-01-06",
    "frac": "0.00339635457941809",
    "table": "all_deaths.rds",
    "field": "NRS.Reg.Date",
    "folder": "/conf/EAVE/GPanalysis/data",
    "date_last_modified": "2022-08-11 11:36:22"
  },
  {
    "value": "2021-01-26",
    "frac": "0.00328314276010415",
    "table": "all_deaths.rds",
    "field": "NRS.Reg.Date",
    "folder": "/conf/EAVE/GPanalysis/data",
    "date_last_modified": "2022-08-11 11:36:22"
  },
  {
    "value": "2022-01-06",
    "frac": "0.00328314276010415",
    "table": "all_deaths.rds",
    "field": "NRS.Reg.Date",
    "folder": "/conf/EAVE/GPanalysis/data",
    "date_last_modified": "2022-08-11 11:36:22"
  },
  {
    "value": "2020-04-07",
    "frac": "0.00316993094079022",
    "table": "all_deaths.rds",
    "field": "NRS.Reg.Date",
    "folder": "/conf/EAVE/GPanalysis/data",
    "date_last_modified": "2022-08-11 11:36:22"
  },
  {
    "value": "2021-01-07",
    "frac": "0.00316993094079022",
    "table": "all_deaths.rds",
    "field": "NRS.Reg.Date",
    "folder": "/conf/EAVE/GPanalysis/data",
    "date_last_modified": "2022-08-11 11:36:22"
  },
  {
    "value": "2020-11-23",
    "frac": "0.00305671912147628",
    "table": "all_deaths.rds",
    "field": "NRS.Reg.Date",
    "folder": "/conf/EAVE/GPanalysis/data",
    "date_last_modified": "2022-08-11 11:36:22"
  }
]
